flaskool/__init__.py
flaskool-0.1.dist-info/METADATA
flaskool-0.1.dist-info/RECORD
flaskool-0.1.dist-info/WHEEL
flaskool-0.1.dist-info/top_level.txt
