Metadata-Version: 2.1
Name: flaskool
Version: 0.1
Summary: Starter Kit for Building Web Application with Flask
Home-page: https://github.com/kwanstyle/flaskool
Author: Kevin Wang
Author-email: zikevin.wang@yahoo.com
License: MIT
Platform: UNKNOWN
